{
    "uuids": {
        "phone_id": "88d7a43e-e3f2-4233-97e2-8b296215df2e",
        "uuid": "4fe644a7-02c1-4dc1-aee3-6c106231bc0f",
        "client_session_id": "43639cdb-9229-40ca-9ef6-d930f0546c02",
        "advertising_id": "c92913ac-eb2c-4811-8604-7fb94db192bd",
        "android_device_id": "android-772f4678fb16f4c9",
        "request_id": "1dfdc095-cffd-4a42-aa35-830a45354750",
        "tray_session_id": "e3494073-20a9-4812-8628-3e5d27d59829"
    },
    "mid": "Z5VfOgABAAHRmyM3zBUi4LYBdvol",
    "ig_u_rur": null,
    "ig_www_claim": null,
    "authorization_data": {
        "ds_user_id": "70684503354",
        "sessionid": "70684503354%3AGaS1QzRYTr8id2%3A17%3AAYfiZv5oplObYm0foyaIZkRuss4VAE5WyHKi1FPSbw"
    },
    "cookies": {},
    "last_login": 1737842500.9971635,
    "device_settings": {
        "app_version": "269.0.0.18.75",
        "android_version": 26,
        "android_release": "8.0.0",
        "dpi": "480dpi",
        "resolution": "1080x1920",
        "manufacturer": "OnePlus",
        "device": "devitron",
        "model": "6T Dev",
        "cpu": "qcom",
        "version_code": "314665256"
    },
    "user_agent": "Instagram 269.0.0.18.75 Android (26/8.0.0; 480dpi; 1080x1920; OnePlus; 6T Dev; devitron; qcom; en_US; 314665256)",
    "country": "US",
    "country_code": 1,
    "locale": "en_US",
    "timezone_offset": -14400
}